shared_service
