Metadata-Version: 2.1
Name: afex-devtools
Version: 0.3
Requires-Python: >=3.9
Requires-Dist: grpcio-tools==1.50.0
Requires-Dist: Django==4.1.6
Requires-Dist: djangorestframework==3.14.0
Requires-Dist: any-case==0.1.6
